GANerAid/__init__.py
GANerAid/data_preprocessor.py
GANerAid/evaluation_report.py
GANerAid/experiment_runner.py
GANerAid/gan_trainer.py
GANerAid/ganeraid.py
GANerAid/logger.py
GANerAid/main.py
GANerAid/model.py
GANerAid/utils.py
GANerAid-1.8.dist-info/LICENSE
GANerAid-1.8.dist-info/METADATA
GANerAid-1.8.dist-info/WHEEL
GANerAid-1.8.dist-info/top_level.txt
GANerAid-1.8.dist-info/RECORD
